{
  "project_info": {
    "project_number": "166310370081",
    "project_id": "chatkotlin-879ef",
    "storage_bucket": "chatkotlin-879ef.appspot.com"
  },
  "client": [
    {
      "client_info": {
        "mobilesdk_app_id": "1:166310370081:android:b50584240c8f6cfd72fc60",
        "android_client_info": {
          "package_name": "com.pedmar.chatkotlin"
        }
      },
      "oauth_client": [],
      "api_key": [
        {
          "current_key": "AIzaSyCFPYaTCOKMHR_cL-ld0no3muUwsf7ml_A"
        }
      ],
      "services": {
        "appinvite_service": {
          "other_platform_oauth_client": []
        }
      }
    }
  ],
  "configuration_version": "1"
}